libprocess/__init__.py
libprocess/_utils/image.py
libprocess/_utils/language.py
libprocess/david_rumsey_map_collection/__init__.py
libprocess/david_rumsey_map_collection/_process_metadata.py
libprocess/david_rumsey_map_collection/_querier.py
libprocess/david_rumsey_map_collection/_schema.py
libprocess/gallica/__init__.py
libprocess/gallica/_process_metadata.py
libprocess/gallica/_querier.py
libprocess/gallica/_schema.py
libprocess/gallica/_utils.py
libprocess/internet_archive/__init__.py
libprocess/internet_archive/_process_metadata.py
libprocess/internet_archive/_querier.py
libprocess/internet_archive/_schema.py
libprocess/library_of_congress/__init__.py
libprocess/library_of_congress/_process_metadata.py
libprocess/library_of_congress/_querier.py
libprocess/library_of_congress/_schema.py
libprocess/typing.py
libprocess-0.1.4.dist-info/LICENSE
libprocess-0.1.4.dist-info/METADATA
libprocess-0.1.4.dist-info/WHEEL
libprocess-0.1.4.dist-info/RECORD
