Metadata-Version: 2.1
Name: libprocess
Version: 0.1.4
Summary: 
Author: Yu Zhang
Author-email: yuzhang94@outlook.com
Requires-Python: >=3.10,<3.13
Classifier: Programming Language :: Python :: 3
Classifier: Programming Language :: Python :: 3.10
Classifier: Programming Language :: Python :: 3.11
Requires-Dist: html2text (>=2020.1.16,<2021.0.0)
Requires-Dist: imagehash (>=4.3.1,<5.0.0)
Requires-Dist: jsonschema (>=4.18.3,<5.0.0)
Requires-Dist: langcodes (>=3.3.0,<4.0.0)
Requires-Dist: langdetect (>=1.0.9,<2.0.0)
Requires-Dist: language-data (>=1.1,<2.0)
Requires-Dist: libquery (>=0.1.1,<0.2.0)
Requires-Dist: nltk (>=3.8.1,<4.0.0)
Requires-Dist: tqdm (>=4.65.0,<5.0.0)
